{
  "data": {
    "marketing-pricing-title": "Pricing — price plans for coworking spaces | andCards Suite",
    "marketing-pricing-description": "andCards pricing, fee, request demo, coworking space software price, coworking space app price",
    "marketing-pricing-any-country": "Any country",
    "marketing-pricing-basic-features": "Essential features",
    "marketing-pricing-basic-features-announcements-with-push-notifications": "Send notices with push notifications",
    "marketing-pricing-basic-features-community-directory-and-search": "Community directory and search",
    "marketing-pricing-basic-features-credit-based-booking": "Credit-based room booking",
    "marketing-pricing-basic-features-internal-booking-system": "Internal booking system",
    "marketing-pricing-country-korea": "Korea",
    "marketing-pricing-country-usa": "USA",
    "marketing-pricing-country-ukraine": "Ukraine",
    "marketing-pricing-external": "External Meeting Room Booking",
    "marketing-pricing-external-price": "5% of transaction",
    "marketing-pricing-headline": "Get your own coworking space app",
    "marketing-pricing-item": "Item",
    "marketing-pricing-meeting-room": "Meeting Room",
    "marketing-pricing-notice-advanced": "All prices are indicative and subject to applicable taxes in your country and payment method fees. At the moment, we offer services in South Korea only. If you live in another country, please contact us for a price estimate.",
    "marketing-pricing-notice-essential": "All prices are per meeting room per month. If you can't see your country in the list, please contact us and we'll provide a rate.",
    "marketing-pricing-subscriptions": "Membership Subscriptions",
    "marketing-pricing-subscriptions-price": "1% of transaction",
    "marketing-pricing-pro-features": "Advanced features",
    "marketing-pricing-pro-features-external-booking-system": "External booking system",
    "marketing-pricing-pro-features-recurring-membership": "Recurring membership subscriptions",
    "marketing-pricing-request-demo": "Request free demo",
    "marketing-pricing-request-demo-email-placeholder": "Type your email",
    "marketing-pricing-request-demo-text": "Get a free 2 week trial, no credit card required! 🎁",
    "marketing-pricing-smart-lock": "Meeting Room with Smart Lock",
    "marketing-pricing-subheadline": "Manage everything — from membership to space."
  }
}
