{
  "data": {

    "marketing-pricing-basic-features": "Базовые функции.",
    "marketing-pricing-basic-features-announcements-with-push-notifications": "Push уведомления",
    "marketing-pricing-basic-features-community-directory-and-search": "Поиск и сортировка по гильдиям участников",
    "marketing-pricing-basic-features-credit-based-booking": "Кредитная система резерваций комнат",
    "marketing-pricing-basic-features-internal-booking-system": "Внутренняя система резервации",
    "marketing-pricing-basic-features-public-profile-at": "Публичный профайл на {andcardsUrl}",
    "marketing-pricing-basic-price": "$20 за переговорную комнату",
    "marketing-pricing-description": "Бесплатно для индивидуальных пользователей, недорого для коворкингов и доступная подписка для компаний. Начните строить свое сообщество прямо сейчас с бесплатной пробной версии!",
    "marketing-pricing-headline": "Получите свое приложение для коворкинга!",
    "marketing-pricing-notice": "Все цены являются ориентировочными и подлежат налогообложению в вашей стране. Пожалуйста, сконтактируйтесь с нами для уточнения цены.",
    "marketing-pricing-pro-price": "10% от транзакции",
    "marketing-pricing-pro-features": "Расширенные функции",
    "marketing-pricing-pro-features-external-booking-system": "Внешняя система резервации",
    "marketing-pricing-pro-features-recurring-membership": "Оплата подписок на коворкинг через приложение",
    "marketing-pricing-request-demo": "Запросить демо",
    "marketing-pricing-subheadline": "Управляй всем — начиная с члества в коворкинге, заканчивая организацией пространства.",
    "marketing-pricing-title": "Цены — тарифные планы для коворкингов и компаний | andCards" 
  }
}
