{
  "data": {
    "marketing-page-demo-meta-title": "Buchen Sie Ihre Demo | andcards",
    "marketing-page-demo-meta-description": "andcards demo. Vereinbaren Sie einen kostenlosen Demo-Anruf mit uns, um andcards in Aktion zu sehen. andcards ist eine Softwarelösung, die Ihr Coworking Business wachsen lässt.",
    "marketing-page-demo-title": "Besser einmal sehen als hundertmal hören.",
    "marketing-page-demo-description": "Fordern Sie eine Testversion von andcards mit einem unserer Coworking-Software-Spezialisten an. Wir können mehr über Ihre Bedürfnisse erfahren, Fragen beantworten und prüfen, wie Ihnen und Ihrem Coworking Space mit andcards geholfen werden kann."
  }
}
